etc/pccold.conf
pccold/__init__.py
pccold/bypyrm.py
pccold/config.py
pccold/pccold.py
pccold/pccold_cli.py
pccold/tail_call.py
pccold/tools.py
pccold/videodownload.py
pccold/wsdanmu.py
pccold-0.32.data/scripts/pccold
pccold-0.32.data/scripts/pccoldcli
pccold-0.32.data/scripts/pccolddanmu
pccold-0.32.data/scripts/pccoldvideo
pccold-0.32.data/scripts/pccoldvideolist
plugins/pccoldtv.py
pccold-0.32.dist-info/LICENSE
pccold-0.32.dist-info/METADATA
pccold-0.32.dist-info/WHEEL
pccold-0.32.dist-info/top_level.txt
pccold-0.32.dist-info/RECORD
